mag_db/__init__.py
mag_db/bean/__init__.py
mag_db/bean/column.py
mag_db/bean/datasource.py
mag_db/bean/db_list.py
mag_db/bean/db_page.py
mag_db/bean/foreign_key.py
mag_db/bean/primary_key.py
mag_db/bean/table.py
mag_db/bean/table_info.py
mag_db/builder/__init__.py
mag_db/builder/alter.py
mag_db/builder/base_sql.py
mag_db/builder/create.py
mag_db/builder/delete.py
mag_db/builder/drop.py
mag_db/builder/insert.py
mag_db/builder/load_data.py
mag_db/builder/select.py
mag_db/builder/sql_builder.py
mag_db/builder/update.py
mag_db/builder/where.py
mag_db/core/__init__.py
mag_db/core/base_dao.py
mag_db/core/db_session.py
mag_db/core/simple_dao.py
mag_db/core/transaction.py
mag_db/core/transaction_cache.py
mag_db/data/__init__.py
mag_db/data/column_names_mapping.py
mag_db/data/db_output.py
mag_db/data/index_parameters.py
mag_db/data/parameter_cache.py
mag_db/data/result_set_helper.py
mag_db/enums/__init__.py
mag_db/enums/db_type.py
mag_db/enums/engine_type.py
mag_db/enums/operator_type.py
mag_db/enums/oracle_convert_type.py
mag_db/enums/postgres_convert_type.py
mag_db/enums/relation.py
mag_db/enums/sql_server_convert_type.py
mag_db/enums/sql_type.py
mag_db/enums/synchron_mode.py
mag_db/enums/transaction_type.py
mag_db/handler/__init__.py
mag_db/handler/bool_type_handler.py
mag_db/handler/bytes_type_handler.py
mag_db/handler/date_type_handler.py
mag_db/handler/datetime_type_handler.py
mag_db/handler/decimal_type_handler.py
mag_db/handler/dict_type_handler.py
mag_db/handler/float_type_handler.py
mag_db/handler/int_type_handler.py
mag_db/handler/list_type_handler.py
mag_db/handler/none_type_handler.py
mag_db/handler/string_type_handler.py
mag_db/handler/time_type_handler.py
mag_db/handler/tuple_type_handler.py
mag_db/handler/type_constant.py
mag_db/handler/type_handler.py
mag_db/handler/type_handler_factory.py
mag_db/handler/__pycache__/__init__.cpython-312.pyc
mag_db/handler/__pycache__/decimal_type_handler.cpython-312.pyc
mag_db/manager/__init__.py
mag_db-0.1.55.dist-info/METADATA
mag_db-0.1.55.dist-info/WHEEL
mag_db-0.1.55.dist-info/top_level.txt
mag_db-0.1.55.dist-info/RECORD
