Metadata-Version: 2.4
Name: mag_db
Version: 0.1.55
Summary: 数据库工具包
Home-page: http://gitlab.magnetitech.com:8088/sources/frame/py-frame/mag_db.git
Author: xlcao
Author-email: xl_cao@hotmail.com
Classifier: Programming Language :: Python :: 3
Classifier: License :: OSI Approved :: MIT License
Classifier: Operating System :: OS Independent
Requires-Python: >=3.6
Dynamic: author
Dynamic: author-email
Dynamic: classifier
Dynamic: description
Dynamic: description-content-type
Dynamic: home-page
Dynamic: requires-python
Dynamic: summary
